{
  "$schema": "https://json-schema.org/draft/2020-12/schema",
  "$id": "https://do-du-yuxuan.github.io/pascal-layout-auditor/schema/parser-normalized-plan-1.0.json",
  "title": "Pascal Layout Auditor evaluation handoff",
  "type": "object",
  "required": ["schemaVersion", "source", "units", "levels", "zones", "spaces", "walls", "doors", "windows", "furniture", "equipment", "columns", "shafts", "stairs", "relationships", "diagnostics"],
  "properties": {
    "schemaVersion": { "const": "1.0" },
    "source": { "type": "object", "required": ["format", "rootNodeIds"], "properties": { "format": { "const": "Pascal JSON" }, "rootNodeIds": { "type": "array", "items": { "type": "string" } } } },
    "units": { "type": "object", "required": ["length", "area", "angles", "planCoordinates", "svgProjection"] },
    "levels": { "type": "array", "items": { "$ref": "#/$defs/baseNode" } },
    "zones": { "type": "array", "items": { "$ref": "#/$defs/spatialRegion" } },
    "spaces": { "type": "array", "items": { "$ref": "#/$defs/spatialRegion" } },
    "walls": { "type": "array", "items": { "$ref": "#/$defs/wall" } },
    "doors": { "type": "array", "items": { "$ref": "#/$defs/opening" } },
    "windows": { "type": "array", "items": { "$ref": "#/$defs/opening" } },
    "furniture": { "type": "array", "items": { "$ref": "#/$defs/item" } },
    "equipment": { "type": "array", "items": { "$ref": "#/$defs/item" } },
    "columns": { "type": "array", "items": { "$ref": "#/$defs/item" } },
    "shafts": { "type": "array", "items": { "$ref": "#/$defs/baseNode" } },
    "stairs": { "type": "array", "items": { "$ref": "#/$defs/baseNode" } },
    "relationships": { "type": "object", "required": ["parentChild", "levelMembership", "hostedOpenings", "wallConnections"] },
    "diagnostics": { "type": "array" }
  },
  "$defs": {
    "point": { "type": "array", "prefixItems": [{ "type": "number" }, { "type": "number" }], "minItems": 2, "maxItems": 2 },
    "baseNode": { "type": "object", "required": ["id", "rawPascalId", "parentId", "levelId", "visible"], "properties": { "id": { "type": "string" }, "rawPascalId": { "type": "string" }, "name": { "type": ["string", "null"] }, "parentId": { "type": ["string", "null"] }, "levelId": { "type": ["string", "null"] }, "visible": { "type": "boolean" } } },
    "spatialRegion": { "allOf": [{ "$ref": "#/$defs/baseNode" }, { "type": "object", "required": ["outline", "areaSquareMeters"], "properties": { "outline": { "type": "array", "items": { "$ref": "#/$defs/point" } }, "areaSquareMeters": { "type": ["number", "null"] } } }] },
    "wall": { "allOf": [{ "$ref": "#/$defs/baseNode" }, { "type": "object", "required": ["start", "end", "thicknessMeters", "curveOffsetMeters", "footprintValidation"], "properties": { "start": { "anyOf": [{ "$ref": "#/$defs/point" }, { "type": "null" }] }, "end": { "anyOf": [{ "$ref": "#/$defs/point" }, { "type": "null" }] }, "thicknessMeters": { "type": "number" }, "curveOffsetMeters": { "type": "number" }, "footprintValidation": { "type": "object", "required": ["valid", "codes", "areaSquareMeters"], "properties": { "valid": { "type": "boolean" }, "codes": { "type": "array", "items": { "type": "string" } }, "areaSquareMeters": { "type": "number" } } } } }] },
    "opening": { "allOf": [{ "$ref": "#/$defs/baseNode" }, { "type": "object", "required": ["hostWallId", "rawWallLocalPosition", "widthMeters", "heightMeters"], "properties": { "hostWallId": { "type": ["string", "null"] }, "rawWallLocalPosition": { "type": ["array", "null"] }, "resolvedWorldPosition": { "anyOf": [{ "$ref": "#/$defs/point" }, { "type": "null" }] }, "widthMeters": { "type": ["number", "null"] }, "heightMeters": { "type": ["number", "null"] } } }] },
    "item": { "allOf": [{ "$ref": "#/$defs/baseNode" }, { "type": "object", "required": ["assetId", "category", "dimensionsMeters", "transformStatus"], "properties": { "assetId": { "type": ["string", "null"] }, "category": { "type": ["string", "null"] }, "dimensionsMeters": { "type": ["array", "null"] }, "transformStatus": { "enum": ["ok", "error"] } } }] }
  }
}
